pipfreezer/__init__.py
pipfreezer/cli.py
pipfreezer/package_data.py
pipfreezer/pipfreezer.py
pip_freezer-0.3.8.dist-info/AUTHORS.md
pip_freezer-0.3.8.dist-info/LICENSE
pip_freezer-0.3.8.dist-info/METADATA
pip_freezer-0.3.8.dist-info/WHEEL
pip_freezer-0.3.8.dist-info/entry_points.txt
pip_freezer-0.3.8.dist-info/top_level.txt
pip_freezer-0.3.8.dist-info/RECORD
