Metadata-Version: 2.1
Name: pip-freezer
Version: 0.3.8
Summary: For the organized, but lazy developer, meaning that you'll update a package, but you don't want to be bothered with updating the requirements file. Pip Freezer pins packages no matter which requirements file they live in and maintains your comments and line breaks.
Author-email: Tim Santor <tsantor@xstudios.com>
Project-URL: Repository, https://github.com/tsantor/pip-freezer.git
Project-URL: Issues, https://github.com/tsantor/pip-freezer/issues
Project-URL: Changelog, https://github.com/tsantor/pip-freezer/blob/master/HISTORY.md
Classifier: Development Status :: 5 - Production/Stable
Classifier: Intended Audience :: Developers
Classifier: Natural Language :: English
Classifier: Programming Language :: Python :: 3.8
Classifier: Programming Language :: Python :: 3.9
Classifier: Programming Language :: Python :: 3.10
Classifier: Programming Language :: Python :: 3.11
Classifier: Programming Language :: Python :: 3.12
Requires-Python: >=3.8
License-File: LICENSE
License-File: AUTHORS.md
Requires-Dist: click
Provides-Extra: dev
